{"idx": 1797, "seed_song": {"track_name": "Inner City Blues (make Me Wanna Holler)", "artist_name": "Marvin Gaye"}, "song_the_chain": {"track_name": "In-a-gadda-da-vida", "artist_name": "Iron Butterfly"}, "song_dave": {"track_name": "This Mess We're In", "artist_name": "PJ Harvey"}, "segue_the_chain": "From \u2018Inner\u2019 to \u2018In-A\u2019\u2026.we go to\u2026.", "segue_dave": {"score": "0.55877", "rarity": "0.39693", "unpopularity": "0", "shortness": "1.0", "value": "city", "compare_function": "equal", "line": "A city link, to a song from the album \"Stories From The City, Stories From The Sea\"...", "explanation": "The word city is shared."}}