{"idx": 3426, "seed_song": {"track_name": "Sweet Harmony", "artist_name": "The Beloved"}, "song_the_chain": {"track_name": "Mojo Pin", "artist_name": "Jeff Buckley"}, "song_dave": {"track_name": "Thin Line", "artist_name": "Fury"}, "segue_the_chain": "From Sweet Harmony to a mojos, which is a type of sweet, so\u2026", "segue_dave": {"score": "0.40204", "rarity": "0.54676", "unpopularity": "0.25", "shortness": "0.33333", "value": "1983", "compare_function": "equal", "line": "The Beloved started being a band in 1983, while Fury sadly died in the same year...", "explanation": "The Beloved started being a band in 1983 and Fury died in the same year."}}