{"idx": 3600, "seed_song": {"track_name": "Heartbeats", "artist_name": "Jos\u00e9 Gonz\u00e1lez"}, "song_the_chain": {"track_name": "Midnight City", "artist_name": "M83"}, "song_dave": {"track_name": "You Came", "artist_name": "Kim Wilde"}, "segue_the_chain": "From Jose Gonzalez to Anthony Gonzalez, also known as M83\u2026", "segue_dave": {"score": "0.42159", "rarity": "0.60397", "unpopularity": "0.4", "shortness": "0.25", "value": "2003", "compare_function": "equal", "line": "Jos\u00e9 Gonz\u00e1lez started his music career in 2003, while Kim Wilde's \"You Came\" was released by MCA Records, a record label which dissolved in the same year...", "explanation": "Jos\u00e9 Gonz\u00e1lez started his carrer in the music industry in 2003 and Kim Wilde's \"Close\" was released by MCA Records, a record label that stop existing in the same year."}}