{"idx": 7616, "seed_song": {"track_name": "Daughter", "artist_name": "Loudon Wainwright III"}, "song_the_chain": {"track_name": "Wow", "artist_name": "Prince & 3RDEYEGIRL"}, "song_dave": {"track_name": "The Farmer's Daughter", "artist_name": "Fleetwood Mac"}, "segue_the_chain": "From Loudon Wainwright III to 3RDEYEGIRL and from Daughter to Girl\u2026", "segue_dave": {"score": "0.64219", "rarity": "0.35549", "unpopularity": "0.5", "shortness": "1.0", "value": "daughter", "compare_function": "equal", "line": "A daughter link...", "explanation": "The word daughter is shared."}}